pystrano/__init__.py
pystrano/config.py
pystrano/core.py
pystrano/deploy.py
pystrano-1.1.2.dist-info/LICENSE
pystrano-1.1.2.dist-info/METADATA
pystrano-1.1.2.dist-info/WHEEL
pystrano-1.1.2.dist-info/entry_points.txt
pystrano-1.1.2.dist-info/top_level.txt
pystrano-1.1.2.dist-info/RECORD
