Metadata-Version: 2.2
Name: pystrano
Version: 1.1.2
Summary: A Python package for managing deploying Django applications (like Capistrano for Ruby)
Home-page: https://github.com/lexpank/pystrano
License: MIT License
Project-URL: homepage, https://github.com/lexpank/pystrano
Project-URL: issues, https://github.com/lexpank/pystrano/issues
Keywords: pystrano
Classifier: Intended Audience :: Developers
Classifier: License :: OSI Approved :: MIT License
Classifier: Programming Language :: Python
Classifier: Programming Language :: Python :: 3.10
Classifier: Programming Language :: Python :: 3.12
Requires-Python: >=3.10
License-File: LICENSE
Requires-Dist: fabric<4.0,>=3.2.2
Requires-Dist: click<9.0,>=8.1.7
Requires-Dist: pyyaml<7.0,>=6.0.2
Requires-Dist: python-dotenv<2.0,>=1.0.1
Dynamic: home-page
Dynamic: requires-python
